requestspool.py
requestspool-1.0.1.dist-info/METADATA
requestspool-1.0.1.dist-info/RECORD
requestspool-1.0.1.dist-info/WHEEL
requestspool-1.0.1.dist-info/top_level.txt
